tomate/__init__.py
tomate/cli.py
tomate/assets/bell.wav
tomate-0.1.1.dist-info/DESCRIPTION.rst
tomate-0.1.1.dist-info/METADATA
tomate-0.1.1.dist-info/RECORD
tomate-0.1.1.dist-info/WHEEL
tomate-0.1.1.dist-info/entry_points.txt
tomate-0.1.1.dist-info/metadata.json
tomate-0.1.1.dist-info/top_level.txt
