Metadata-Version: 2.0
Name: tomate
Version: 0.1.1
Summary: A minimalist pomodoro timer
Home-page: https://github.com/abusque/tomate
Author: Antoine Busque
Author-email: antoinebusque@gmail.com
License: MIT
Keywords: pomodoro,timer
Platform: UNKNOWN
Classifier: License :: OSI Approved :: MIT License
Classifier: Programming Language :: Python
Classifier: Programming Language :: Python :: 3
Classifier: Programming Language :: Python :: 3.6
